dodgeball/__init__.py
dodgeball/api/__init__.py
dodgeball/api/dodgeball.py
dodgeball/api/dodgeball_config.py
dodgeball/interfaces/__init__.py
dodgeball/interfaces/api_types.py
dodgeball/utils/__init__.py
dodgeball/utils/logging.py
dodgeball/utils/query_utils.py
dodgeball_server_sdk-1.0.1.dist-info/LICENSE
dodgeball_server_sdk-1.0.1.dist-info/METADATA
dodgeball_server_sdk-1.0.1.dist-info/WHEEL
dodgeball_server_sdk-1.0.1.dist-info/RECORD
